symregg/_binding.cpython-312-darwin.so
symregg/__init__.py
symregg/_binding.pyi
symregg/binding.i
symregg/_binding.py
symregg/typing.py
symregg/binding.py
symregg/__main__.py
symregg/.dylibs/libnlopt.1.0.0.dylib
symregg-1.0.4.dist-info/RECORD
symregg-1.0.4.dist-info/WHEEL
symregg-1.0.4.dist-info/entry_points.txt
symregg-1.0.4.dist-info/top_level.txt
symregg-1.0.4.dist-info/METADATA
symregg-1.0.4.dist-info/licenses/LICENSE
