Metadata-Version: 2.4
Name: symregg
Version: 1.0.4
Summary: CLI and Python binding for SymRegg algorithm.
Author-email: Fabricio Olivetti <folivetti@users.noreply.github.com>
License:                     GNU GENERAL PUBLIC LICENSE
Classifier: Operating System :: MacOS
Classifier: Operating System :: Microsoft :: Windows
Classifier: Operating System :: POSIX :: Linux
Classifier: Programming Language :: Python :: 3.9
Classifier: Programming Language :: Python :: 3.10
Classifier: Programming Language :: Python :: 3.11
Classifier: Programming Language :: Python :: 3.12
Classifier: Programming Language :: Python :: 3.13
Classifier: Programming Language :: Python :: Implementation :: CPython
Requires-Python: >=3.9
License-File: LICENSE
Requires-Dist: typing_extensions<5,>=4.6; python_version < "3.8"
Requires-Dist: numpy>=2
Requires-Dist: pandas>=2.2
Requires-Dist: scikit-learn>=1.6
Provides-Extra: mypy
Requires-Dist: types_setuptools>=45; extra == "mypy"
Dynamic: license-file
